boto/__init__.py
boto/auth.py
boto/auth_handler.py
boto/compat.py
boto/connection.py
boto/endpoints.json
boto/endpoints.py
boto/exception.py
boto/handler.py
boto/https_connection.py
boto/jsonresponse.py
boto/plugin.py
boto/provider.py
boto/regioninfo.py
boto/requestlog.py
boto/resultset.py
boto/storage_uri.py
boto/utils.py
boto/awslambda/__init__.py
boto/awslambda/exceptions.py
boto/awslambda/layer1.py
boto/beanstalk/__init__.py
boto/beanstalk/exception.py
boto/beanstalk/layer1.py
boto/beanstalk/response.py
boto/beanstalk/wrapper.py
boto/cacerts/__init__.py
boto/cacerts/cacerts.txt
boto/cloudformation/__init__.py
boto/cloudformation/connection.py
boto/cloudformation/stack.py
boto/cloudformation/template.py
boto/cloudfront/__init__.py
boto/cloudfront/distribution.py
boto/cloudfront/exception.py
boto/cloudfront/identity.py
boto/cloudfront/invalidation.py
boto/cloudfront/logging.py
boto/cloudfront/object.py
boto/cloudfront/origin.py
boto/cloudfront/signers.py
boto/cloudhsm/__init__.py
boto/cloudhsm/exceptions.py
boto/cloudhsm/layer1.py
boto/cloudsearch/__init__.py
boto/cloudsearch/document.py
boto/cloudsearch/domain.py
boto/cloudsearch/layer1.py
boto/cloudsearch/layer2.py
boto/cloudsearch/optionstatus.py
boto/cloudsearch/search.py
boto/cloudsearch/sourceattribute.py
boto/cloudsearch2/__init__.py
boto/cloudsearch2/document.py
boto/cloudsearch2/domain.py
boto/cloudsearch2/exceptions.py
boto/cloudsearch2/layer1.py
boto/cloudsearch2/layer2.py
boto/cloudsearch2/optionstatus.py
boto/cloudsearch2/search.py
boto/cloudsearchdomain/__init__.py
boto/cloudsearchdomain/exceptions.py
boto/cloudsearchdomain/layer1.py
boto/cloudtrail/__init__.py
boto/cloudtrail/exceptions.py
boto/cloudtrail/layer1.py
boto/codedeploy/__init__.py
boto/codedeploy/exceptions.py
boto/codedeploy/layer1.py
boto/cognito/__init__.py
boto/cognito/identity/__init__.py
boto/cognito/identity/exceptions.py
boto/cognito/identity/layer1.py
boto_mws-2.46.1.dist-info/DESCRIPTION.rst
boto_mws-2.46.1.dist-info/METADATA
boto_mws-2.46.1.dist-info/RECORD
boto_mws-2.46.1.dist-info/WHEEL
boto_mws-2.46.1.dist-info/metadata.json
boto_mws-2.46.1.dist-info/top_level.txt
