Metadata-Version: 2.0
Name: boto-mws
Version: 2.46.1
Summary: Amazon Web Services Library
Home-page: https://github.com/boto/boto/
Author: Mitch Garnaat
Author-email: mitch@garnaat.com
License: MIT
Platform: Posix; MacOS X; Windows
Classifier: Development Status :: 5 - Production/Stable
Classifier: Intended Audience :: Developers
Classifier: License :: OSI Approved :: MIT License
Classifier: Operating System :: OS Independent
Classifier: Topic :: Internet
Classifier: Programming Language :: Python :: 2
Classifier: Programming Language :: Python :: 2.6
Classifier: Programming Language :: Python :: 2.7
Classifier: Programming Language :: Python :: 3
Classifier: Programming Language :: Python :: 3.3
Classifier: Programming Language :: Python :: 3.4
